{
  "date": "2020-03-13T05:59:55.814Z",
  "title": "ニュースフィードが追加されました",
  "slug": "add-news",
  "category": "info",
  "description": "ニュースフィードが追加されました!",
  "body": "## 最新情報\n\n* [/checkコマンド](https://morino.party/command)が追加されました（'20/11/26）\n* [ミニイベント開催中・新嘗祭（にいなめさい）](https://morino.party/news/minievent1)（'20/11/21～/11/29）\n* [特定ブロックの設置数制限について](https://morino.party/news/insights)（'20/11/21）\n* [負荷軽減の為に気を付ける事](https://wiki.morino.party/antilag)（'20/11/21）\n* [サーバーへの寄付の受付方法が変更されました](https://morino.party/donate)（'20/11/12）\n\n## お知らせ\n\n* お知らせ格納予定地\n\n## イベント情報\n\n* [ミニイベント開催中・新嘗祭（にいなめさい）](https://morino.party/news/minievent1)（'20/11/21～/11/29）\n* [Halloween仮装パーティ・お披露目](https://wiki.morino.party/halloween_20201031)（'20/10/31）\n* [Halloween仮装パーティ・告知](https://morino.party/news/halloweenparty)（'20/10/31）\n* [2020秋の建築大会・結果発表](https://morino.party/news/buildevent2020-10result)（'20/09/26～10/04）\n* [2020秋の建築大会・開催予告](https://morino.party/news/buildevent-9-26)（'20/09/26～10/04）\n* [さらに過去のイベント](https://wiki.morino.party/old-event)\n\n## リンク\n\n* [もりのパーティ公式HP](https://morino.party)\n* [もりのパーティ公式Wiki](https://wiki.morino.party)：サーバー内の有志が自由に編集している情報サイト\n* [お問い合わせフォーム](https://forms.gle/GpYYVKpYkXgjQCmU7)：ご意見・相談・通報などはこちらから\n\n| a   | b   | c              |\n| --- | --- | -------------- |\n| a1  | b1  |                |\n|     | b2  | c2<br>cc<br>cc |\n|     |     | c3             |\n\n<br>\n| a   | b   | c              | \n| -- | :-: | -------------: | \n| abcdefghijklmnopqrstuvwxyz  | b1  |                | \n|     | b2  | c2<br>cc<br>cc | \n|     |     | c3             | \n<br>\n|&nbsp;&nbsp;&nbsp;&nbsp;a&nbsp; | b   | c              | \n| -- | :-: | -------------: | \n| ab  | b1  |                | \n|     | b2  | c2| \n|     |&nbsp;&nbsp;&nbsp;&nbsp;c2   | c3             |"
}